assets/copyright.png
assets/main.ico
assets/resource/0circle.png
assets/resource/0circle_faded.png
assets/resource/3d.png
assets/resource/3d.psd
assets/resource/3dFaded.png
assets/resource/Eraser.png
assets/resource/EraserFaded.png
assets/resource/EraserX.png
assets/resource/EraserXFaded.png
assets/resource/Eraser_icon.svg
assets/resource/Hand.png
assets/resource/HandIcons_0.png
assets/resource/Hand_IX.png
assets/resource/Hand_IXFaded.png
assets/resource/Handsqueezed.png
assets/resource/Handwriting (copy).png
assets/resource/Handwriting.png
assets/resource/HandwritingMinus.png
assets/resource/HandwritingMinusX.png
assets/resource/HandwritingPlus.png
assets/resource/HandwritingPlusX.png
assets/resource/Move_icon.svg
assets/resource/PngItem_2422924.png
assets/resource/about.png
assets/resource/about_logo.png
assets/resource/about_logo0.png
assets/resource/action_check.png
assets/resource/action_check_OFF.png
assets/resource/arrow).png
assets/resource/arrow.png
assets/resource/arrowFaded.png
assets/resource/arrow_org.png
assets/resource/arrow_org.png.png
assets/resource/arrows.png
assets/resource/authors.mp4
assets/resource/batch.png
assets/resource/box.png
assets/resource/check-image-icon-0.jpg
assets/resource/circle.png
assets/resource/circle_faded.png
assets/resource/circle_or.png
assets/resource/close.png
assets/resource/close_bg.png
assets/resource/contour.png
assets/resource/contour.svg
assets/resource/contourFaded.png
assets/resource/contourX.png
assets/resource/contourXFaded.png
assets/resource/dti.png
assets/resource/dti0.png
assets/resource/dti222.png
assets/resource/dti_or.png
assets/resource/eco.png
assets/resource/eco22.png
assets/resource/eco_old.png
assets/resource/eco_or.png
assets/resource/eco_or2.png
assets/resource/eco_seg.png
assets/resource/eco_seg_old.png
assets/resource/explorer.png
assets/resource/export.png
assets/resource/hand-grab-icon-10.jpg
assets/resource/hand-grab-icon-25.jpg
assets/resource/horizontalview.png
melage-2.1.23.dist-info/METADATA
melage-2.1.23.dist-info/WHEEL
melage-2.1.23.dist-info/entry_points.txt
melage-2.1.23.dist-info/top_level.txt
melage-2.1.23.dist-info/RECORD
