Metadata-Version: 2.4
Name: melage
Version: 2.1.23
Summary: MELAGE: An open-source Python toolkit for medical imaging (3D MRI & 3D ultrasound, 3D CT, etc.).
Author-email: Bahram Jafrasteh <b.jafrasteh@gmail.com>
Project-URL: Homepage, https://github.com/BahramJafrasteh/MELAGE
Project-URL: Repository, https://github.com/BahramJafrasteh/MELAGE
Project-URL: Issues, https://github.com/BahramJafrasteh/MELAGE/issues
Project-URL: Documentation, https://github.com/BahramJafrasteh/MELAGE#readme
Keywords: neuroimaging,MRI,ultrasound,segmentation,visualization,neonatal,medical-imaging,deep learning
Classifier: Development Status :: 3 - Alpha
Classifier: Intended Audience :: Science/Research
Classifier: License :: OSI Approved :: Apache Software License
Classifier: Programming Language :: Python
Classifier: Programming Language :: Python :: 3
Classifier: Programming Language :: Python :: 3 :: Only
Classifier: Programming Language :: Python :: 3.9
Classifier: Programming Language :: Python :: 3.10
Classifier: Programming Language :: Python :: 3.11
Classifier: Programming Language :: Python :: 3.12
Classifier: Operating System :: OS Independent
Classifier: Topic :: Scientific/Engineering
Classifier: Topic :: Scientific/Engineering :: Medical Science Apps.
Classifier: Topic :: Scientific/Engineering :: Image Processing
Requires-Python: >=3.9
Requires-Dist: numpy
Requires-Dist: scipy
Requires-Dist: matplotlib
Requires-Dist: Pillow
Requires-Dist: PyQt5
Requires-Dist: PyOpenGL
Requires-Dist: opencv-python-headless
Requires-Dist: nibabel
Requires-Dist: pydicom
Requires-Dist: scikit-image
Requires-Dist: scikit-learn
Requires-Dist: shapely
Requires-Dist: SimpleITK
Requires-Dist: antspyx
Provides-Extra: ai
Requires-Dist: torch; extra == "ai"
Requires-Dist: einops; extra == "ai"
Provides-Extra: bet
Requires-Dist: numba; extra == "bet"
Requires-Dist: trimesh; extra == "bet"
Provides-Extra: processing
Requires-Dist: vtk; extra == "processing"
Provides-Extra: reports
Requires-Dist: dominate; extra == "reports"
Provides-Extra: all
Requires-Dist: melage[ai,processing,reports]; extra == "all"
Provides-Extra: bids
Requires-Dist: pybids>=0.16; extra == "bids"
Requires-Dist: bids-validator>=1.14; python_version < "3.12" and extra == "bids"
Provides-Extra: dev
Requires-Dist: pytest>=8.0; extra == "dev"
Requires-Dist: pytest-cov>=5.0; extra == "dev"
Requires-Dist: ruff>=0.4; extra == "dev"
Requires-Dist: mypy>=1.8; extra == "dev"
Requires-Dist: build>=1.2; extra == "dev"
Requires-Dist: twine>=5.0; extra == "dev"
